async_timeout/__init__.py
async_timeout/py.typed
async_timeout-4.0.1.dist-info/LICENSE
async_timeout-4.0.1.dist-info/METADATA
async_timeout-4.0.1.dist-info/WHEEL
async_timeout-4.0.1.dist-info/top_level.txt
async_timeout-4.0.1.dist-info/zip-safe
async_timeout-4.0.1.dist-info/RECORD
