Metadata-Version: 2.1
Name: async-timeout
Version: 4.0.1
Summary: Timeout context manager for asyncio programs
Home-page: https://github.com/aio-libs/async-timeout
Author: Andrew Svetlov <andrew.svetlov@gmail.com>
Author-email: andrew.svetlov@gmail.com
License: Apache 2
Project-URL: Chat: Gitter, https://gitter.im/aio-libs/Lobby
Project-URL: CI: GitHub Actions, https://github.com/aio-libs/async-timeout/actions
Project-URL: Coverage: codecov, https://codecov.io/github/aio-libs/async-timeout
Project-URL: GitHub: issues, https://github.com/aio-libs/async-timeout/issues
Project-URL: GitHub: repo, https://github.com/aio-libs/async-timeout
Platform: UNKNOWN
Classifier: Development Status :: 5 - Production/Stable
Classifier: Topic :: Software Development :: Libraries
Classifier: Framework :: AsyncIO
Classifier: Intended Audience :: Developers
Classifier: License :: OSI Approved :: Apache Software License
Classifier: Programming Language :: Python
Classifier: Programming Language :: Python :: 3
Classifier: Programming Language :: Python :: 3 :: Only
Classifier: Programming Language :: Python :: 3.6
Classifier: Programming Language :: Python :: 3.7
Classifier: Programming Language :: Python :: 3.8
Classifier: Programming Language :: Python :: 3.9
Classifier: Programming Language :: Python :: 3.10
Requires-Python: >=3.6
License-File: LICENSE
